foliant/contrib/__init__.py
foliant/contrib/chapters.py
foliantcontrib.utils.chapters-1.0.4.dist-info/LICENSE
foliantcontrib.utils.chapters-1.0.4.dist-info/METADATA
foliantcontrib.utils.chapters-1.0.4.dist-info/WHEEL
foliantcontrib.utils.chapters-1.0.4.dist-info/top_level.txt
foliantcontrib.utils.chapters-1.0.4.dist-info/RECORD
